arkhon_memory_st-0.1.1.dist-info/licenses/LICENSE
arkhon_st/__init__.py
arkhon_st/sillytavern_bridge.py
arkhon_st/st_schemas.py
arkhon_memory_st-0.1.1.dist-info/METADATA
arkhon_memory_st-0.1.1.dist-info/WHEEL
arkhon_memory_st-0.1.1.dist-info/top_level.txt
arkhon_memory_st-0.1.1.dist-info/RECORD
