Metadata-Version: 2.4
Name: arkhon-memory-st
Version: 0.1.1
Summary: SillyTavern bridge for Arkhon memory
Author-email: kissg96 <kissg@me.com>
License-Expression: MIT
Project-URL: Homepage, https://github.com/kissg96/arkhon-memory-st
Project-URL: ArkhonMemorySDK, https://github.com/kissg96/arkhon_memory
Requires-Python: >=3.8
License-File: LICENSE
Requires-Dist: arkhon-memory>=0.1.0
Dynamic: license-file
